athenatos3/__init__.py
athenatos3/athenatos3.py
athenatos3-0.0.1.dist-info/LICENSE
athenatos3-0.0.1.dist-info/METADATA
athenatos3-0.0.1.dist-info/WHEEL
athenatos3-0.0.1.dist-info/top_level.txt
athenatos3-0.0.1.dist-info/RECORD
