Metadata-Version: 2.1
Name: athenatos3
Version: 0.0.1
Summary: A small package to connect Athena to S3
Home-page: https://github.com/pypa/sampleproject
Author: zhiyi
Author-email: zyleu@topglove.com.my
License: UNKNOWN
Project-URL: Bug Tracker, https://github.com/pypa/sampleproject/issues
Platform: UNKNOWN
Classifier: Programming Language :: Python :: 3
Classifier: License :: OSI Approved :: MIT License
Classifier: Operating System :: OS Independent
Requires-Python: >=3.6
License-File: LICENSE
